ovos_skill_wolfie/LICENSE
ovos_skill_wolfie/MANIFEST.in
ovos_skill_wolfie/README.md
ovos_skill_wolfie/__init__.py
ovos_skill_wolfie/settingsmeta.json
ovos_skill_wolfie/version.py
ovos_skill_wolfie/gui/all/logo.png
ovos_skill_wolfie/gui/qt5/wolf.qml
ovos_skill_wolfie/locale/ca-es/MiscBlacklist.voc
ovos_skill_wolfie/locale/ca-es/More.voc
ovos_skill_wolfie/locale/ca-es/no_answer.dialog
ovos_skill_wolfie/locale/ca-es/search_wolfie.intent
ovos_skill_wolfie/locale/ca-es/skill.json
ovos_skill_wolfie/locale/da-dk/More.voc
ovos_skill_wolfie/locale/da-dk/no_answer.dialog
ovos_skill_wolfie/locale/da-dk/search_wolfie.intent
ovos_skill_wolfie/locale/da-dk/skill.json
ovos_skill_wolfie/locale/de-de/More.voc
ovos_skill_wolfie/locale/de-de/no_answer.dialog
ovos_skill_wolfie/locale/de-de/search_wolfie.intent
ovos_skill_wolfie/locale/de-de/skill.json
ovos_skill_wolfie/locale/en-us/Help.voc
ovos_skill_wolfie/locale/en-us/MiscBlacklist.voc
ovos_skill_wolfie/locale/en-us/More.voc
ovos_skill_wolfie/locale/en-us/no_answer.dialog
ovos_skill_wolfie/locale/en-us/search_wolfie.intent
ovos_skill_wolfie/locale/en-us/skill.json
ovos_skill_wolfie/locale/es-es/More.voc
ovos_skill_wolfie/locale/es-es/no_answer.dialog
ovos_skill_wolfie/locale/es-es/search_wolfie.intent
ovos_skill_wolfie/locale/eu/More.voc
ovos_skill_wolfie/locale/eu/no_answer.dialog
ovos_skill_wolfie/locale/eu/search_wolfie.intent
ovos_skill_wolfie/locale/fr-fr/More.voc
ovos_skill_wolfie/locale/fr-fr/no_answer.dialog
ovos_skill_wolfie/locale/fr-fr/search_wolfie.intent
ovos_skill_wolfie/locale/gl-es/MiscBlacklist.voc
ovos_skill_wolfie/locale/gl-es/More.voc
ovos_skill_wolfie/locale/gl-es/no_answer.dialog
ovos_skill_wolfie/locale/gl-es/search_wolfie.intent
ovos_skill_wolfie/locale/gl-es/skill.json
ovos_skill_wolfie/locale/it-it/More.voc
ovos_skill_wolfie/locale/it-it/no_answer.dialog
ovos_skill_wolfie/locale/it-it/search_wolfie.intent
ovos_skill_wolfie/locale/pt-pt/More.voc
ovos_skill_wolfie/locale/pt-pt/no_answer.dialog
ovos_skill_wolfie/ovos_skill_wolfie.egg-info/PKG-INFO
ovos_skill_wolfie/ovos_skill_wolfie.egg-info/SOURCES.txt
ovos_skill_wolfie/ovos_skill_wolfie.egg-info/dependency_links.txt
ovos_skill_wolfie/ovos_skill_wolfie.egg-info/entry_points.txt
ovos_skill_wolfie/ovos_skill_wolfie.egg-info/requires.txt
ovos_skill_wolfie/ovos_skill_wolfie.egg-info/top_level.txt
ovos_skill_wolfie-0.5.8.dist-info/LICENSE
ovos_skill_wolfie-0.5.8.dist-info/METADATA
ovos_skill_wolfie-0.5.8.dist-info/WHEEL
ovos_skill_wolfie-0.5.8.dist-info/entry_points.txt
ovos_skill_wolfie-0.5.8.dist-info/top_level.txt
ovos_skill_wolfie-0.5.8.dist-info/RECORD
